contextpack/__init__.py
contextpack/_modidx.py
contextpack/core.py
contextpack-0.0.5.dist-info/LICENSE
contextpack-0.0.5.dist-info/METADATA
contextpack-0.0.5.dist-info/WHEEL
contextpack-0.0.5.dist-info/entry_points.txt
contextpack-0.0.5.dist-info/top_level.txt
contextpack-0.0.5.dist-info/RECORD
